napari_prism/__init__.py
napari_prism/_version.py
napari_prism/constants.py
napari_prism/datasets.py
napari_prism/gr.py
napari_prism/im.py
napari_prism/io.py
napari_prism/napari.yaml
napari_prism/pl.py
napari_prism/pp.py
napari_prism/tl.py
napari_prism/_datasets/__init__.py
napari_prism/_datasets/_datasets.py
napari_prism/models/__init__.py
napari_prism/models/_utils.py
napari_prism/models/adata_ops/__init__.py
napari_prism/models/adata_ops/cell_typing/__init__.py
napari_prism/models/adata_ops/cell_typing/_augmentation.py
napari_prism/models/adata_ops/cell_typing/_clusteval.py
napari_prism/models/adata_ops/cell_typing/_clustsearch.py
napari_prism/models/adata_ops/cell_typing/_embeddings.py
napari_prism/models/adata_ops/cell_typing/_preprocessing.py
napari_prism/models/adata_ops/cell_typing/_tree.py
napari_prism/models/adata_ops/feature_modelling/_discrete.py
napari_prism/models/adata_ops/feature_modelling/_obs.py
napari_prism/models/adata_ops/feature_modelling/_survival.py
napari_prism/models/adata_ops/spatial_analysis/_cell_level.py
napari_prism/models/adata_ops/spatial_analysis/_constants.py
napari_prism/models/adata_ops/spatial_analysis/_obs_level.py
napari_prism/models/adata_ops/spatial_analysis/_utils.py
napari_prism/models/tma_ops/__init__.py
napari_prism/models/tma_ops/_tma_image.py
napari_prism/readers/__init__.py
napari_prism/readers/_readers.py
napari_prism/widgets/__init__.py
napari_prism/widgets/_adata_ops_widget.py
napari_prism/widgets/_api_access.py
napari_prism/widgets/_tma_ops_widget.py
napari_prism/widgets/_widget_utils.py
napari_prism/widgets/adata_ops/__init__.py
napari_prism/widgets/adata_ops/_base_widgets.py
napari_prism/widgets/adata_ops/_cell_typing_widgets.py
napari_prism/widgets/adata_ops/_feature_modelling_widgets.py
napari_prism/widgets/adata_ops/_plot_widgets.py
napari_prism/widgets/adata_ops/_scanpy_widgets.py
napari_prism/widgets/adata_ops/_spatial_analysis_widgets.py
napari_prism/widgets/tma_ops/__init__.py
napari_prism-0.1.7.dist-info/licenses/LICENSE
napari_prism-0.1.7.dist-info/METADATA
napari_prism-0.1.7.dist-info/WHEEL
napari_prism-0.1.7.dist-info/entry_points.txt
napari_prism-0.1.7.dist-info/top_level.txt
napari_prism-0.1.7.dist-info/RECORD
