Metadata-Version: 2.4
Name: napari-prism
Version: 0.1.7
Summary: A Python package for the inteRactive and Integrated analySis of Multiplexed tissue microarrays
Home-page: https://github.com/clinicalomx/napari-prism
Author: Rafael Tubelleza
Author-email: rafaelrtubelleza@gmail.com
License: MIT
Project-URL: Bug Tracker, https://github.com/clinicalomx/napari-prism/issues
Project-URL: Documentation, https://github.com/clinicalomx/napari-prism#README.md
Project-URL: Source Code, https://github.com/clinicalomx/napari-prism
Project-URL: User Support, https://github.com/clinicalomx/napari-prism/issues
Classifier: Development Status :: 2 - Pre-Alpha
Classifier: Framework :: napari
Classifier: Intended Audience :: Science/Research
Classifier: License :: OSI Approved :: MIT License
Classifier: Operating System :: OS Independent
Classifier: Programming Language :: Python
Classifier: Programming Language :: Python :: 3
Classifier: Programming Language :: Python :: 3.10
Classifier: Topic :: Scientific/Engineering :: Image Processing
Requires-Python: >=3.10
License-File: LICENSE
Requires-Dist: numpy
Requires-Dist: magicgui
Requires-Dist: qtpy
Requires-Dist: scikit-image
Requires-Dist: spatialdata>=0.5.0
Requires-Dist: imagecodecs
Requires-Dist: napari[all]
Requires-Dist: napari_matplotlib>=3.0.0
Requires-Dist: napari_spatialdata>=0.5.7
Requires-Dist: dask<2024.11.12
Requires-Dist: matplotlib
Requires-Dist: PyComplexHeatmap
Requires-Dist: scikit-learn
Requires-Dist: cellpose>=3.0.10
Requires-Dist: scanpy>=1.10.0
Requires-Dist: harmonypy
Requires-Dist: phenograph
Requires-Dist: squidpy
Requires-Dist: kneed
Requires-Dist: xarray
Requires-Dist: pyometiff
Requires-Dist: forestplot
Requires-Dist: scikit-survival
Requires-Dist: spatialdata-plot>=0.2.11
Requires-Dist: requests
Provides-Extra: gpu
Requires-Dist: dask-cudf-cu12==24.10.*; extra == "gpu"
Requires-Dist: rapids-singlecell[rapids12]; extra == "gpu"
Provides-Extra: testing
Requires-Dist: tox; extra == "testing"
Requires-Dist: pytest; extra == "testing"
Requires-Dist: pytest-lazy-fixtures; extra == "testing"
Requires-Dist: pytest-cov; extra == "testing"
Requires-Dist: pytest-qt; extra == "testing"
Requires-Dist: napari; extra == "testing"
Requires-Dist: qtpy; extra == "testing"
Provides-Extra: docs
Requires-Dist: ipykernel; extra == "docs"
Requires-Dist: ipython; extra == "docs"
Requires-Dist: myst-nb>=1.1; extra == "docs"
Requires-Dist: myst-parser; extra == "docs"
Requires-Dist: sphinx>=4; extra == "docs"
Requires-Dist: sphinx-autodoc-typehints; extra == "docs"
Requires-Dist: sphinx-book-theme>=1; extra == "docs"
Requires-Dist: sphinx-copybutton; extra == "docs"
Requires-Dist: sphinx-qt-documentation; extra == "docs"
Requires-Dist: sphinxcontrib-bibtex>=1; extra == "docs"
Requires-Dist: sphinx-tabs; extra == "docs"
Requires-Dist: sphinxext-opengraph; extra == "docs"
Dynamic: license-file
